{
  "lastUpdatedBy": "Amelia",
  "lastUpdatedDate": "2018/10/08 10:00:00",
  "entryPageItems": [
    {
      "entryType": "item",
      "entryContent": {
        "imageURL": "https://archive.org/download/LFAEmigre0002/LFA_Emigre_0002_0001.jpg",
        "title": "Emigre #2: The Magazine That Ignores Boundaries",
        "newItem": 0
      },
      "entryURL": "LetArcV1_details.html?LFAitemID=lfa_emigre_0002&LFAPics=Yes"
    },
    {
      "entryType": "item",
      "entryContent": {
        "imageURL": "https://archive.org/download/LFAShepard0062/LFA_Shepard_0062_001.jpg",
        "title": "Birthday card for Gordon, Shepard's son",
        "newItem": 0
      },
      "entryURL": "LetArcV1_details.html?LFAitemID=lfa_shepard_0062&LFAPics=Yes"
    },
    {
      "entryType": "item",
      "entryContent": {
        "imageURL": "https://archive.org/download/LFAShepard0088/LFA_Shepard_0088_001.jpg",
        "title": "Photo of Billboard for Wrigley's DS Fish sign at night NY",
        "newItem": 0
      },
      "entryURL": "LetArcV1_details.html?LFAitemID=lfa_shepard_0088&LFAPics=Yes"
    },
    {
      "entryType": "item",
      "entryContent": {
        "imageURL": "https://archive.org/download/LFAShepard0220/LFA_Shepard_0220_001.jpg",
        "title": "Menu · Marine Bar drinks menu",
        "newItem": 0
      },
      "entryURL": "LetArcV1_details.html?LFAitemID=lfa_shepard_0220&LFAPics=Yes"
    },
    {
      "entryType": "item",
      "entryContent": {
        "imageURL": "https://archive.org/download/LFAShepard0237/LFA_Shepard_0237_001.jpg",
        "title": "Swaps vs Nashua",
        "newItem": 0
      },
      "entryURL": "LetArcV1_details.html?LFAitemID=lfa_shepard_0237&LFAPics=Yes"
    },
    {
      "entryType": "item",
      "entryContent": {
        "imageURL": "https://archive.org/download/LFAShepard0287/LFA_Shepard_0287_001.jpg",
        "title": "Cal Aggies pasted up original artwork",
        "newItem": 0
      },
      "entryURL": "LetArcV1_details.html?LFAitemID=lfa_shepard_0287&LFAPics=Yes"
    },
    {
      "entryType": "item",
      "entryContent": {
        "imageURL": "https://archive.org/download/LFASutnar0017/LFA_Sutnar_0017_001.jpg",
        "title": "Cityscape Print",
        "newItem": 1
      },
      "entryURL": "LetArcV1_details.html?LFAitemID=lfa_sutnar_0017&LFAPics=Yes"
    },
    {
      "entryType": "item",
      "entryContent": {
        "imageURL": "https://archive.org/download/LFASutnar0037/LFA_Sutnar_0037_001.jpg",
        "title": "Poster: Sweet's designs catalogs for buying action.",
        "newItem": 1
      },
      "entryURL": "LetArcV1_details.html?LFAitemID=lfa_sutnar_0037&LFAPics=Yes"
    },
    {
      "entryType": "item",
      "entryContent": {
        "imageURL": "https://archive.org/download/LFASutnar0059/LFA_Sutnar_0059_001.jpg",
        "title": "Herman Nelson Unit Heaters: Horizontal Shaft Propeller-Fan Type",
        "newItem": 1
      },
      "entryURL": "LetArcV1_details.html?LFAitemID=lfa_sutnar_0059&LFAPics=Yes"
    },
    {
      "entryType": "item",
      "entryContent": {
        "imageURL": "https://archive.org/download/LFASutnar0081/LFA_Sutnar_0081_001.jpg",
        "title": "Scovill Condenser Tubes",
        "newItem": 1
      },
      "entryURL": "LetArcV1_details.html?LFAitemID=lfa_sutnar_0081&LFAPics=Yes"
    },
    {
      "entryType": "item",
      "entryContent": {
        "imageURL": "https://archive.org/download/LFAType0009/LFA_Type_0009_001.jpg",
        "title": "Eurostile (Sintesi evolutiva del nostro tempo)",
        "newItem": 0
      },
      "entryURL": "LetArcV1_details.html?LFAitemID=lfa_type_0009&LFAPics=Yes"
    },
    {
      "entryType": "item",
      "entryContent": {
        "imageURL": "https://archive.org/download/LFAType0018/LFA_Type_0018_001.jpg",
        "title": "Fluidum",
        "newItem": 0
      },
      "entryURL": "LetArcV1_details.html?LFAitemID=lfa_type_0018&LFAPics=Yes"
    },
    {
      "entryType": "item",
      "entryContent": {
        "imageURL": "https://archive.org/download/LFAType0021/LFA_Type_0021_001.jpg",
        "title": "Forma [Italic]",
        "newItem": 0
      },
      "entryURL": "LetArcV1_details.html?LFAitemID=lfa_type_0021&LFAPics=Yes"
    },
    {
      "entryType": "item",
      "entryContent": {
        "imageURL": "https://archive.org/download/LFAType0026/LFA_Type_0026_001.jpg",
        "title": "Landi Linear",
        "newItem": 0
      },
      "entryURL": "LetArcV1_details.html?LFAitemID=lfa_type_0026&LFAPics=Yes"
    },
    {
      "entryType": "item",
      "entryContent": {
        "imageURL": "https://archive.org/download/LFAType0028/LFA_Type_0028_001.jpg",
        "title": "Magister: nuova serie corsiva neretta",
        "newItem": 0
      },
      "entryURL": "LetArcV1_details.html?LFAitemID=lfa_type_0028&LFAPics=Yes"
    },
    {
      "entryType": "item",
      "entryContent": {
        "imageURL": "https://archive.org/download/LFAType0033/LFA_Type_0033_001.jpg",
        "title": "Neon",
        "newItem": 0
      },
      "entryURL": "LetArcV1_details.html?LFAitemID=lfa_type_0033&LFAPics=Yes"
    },
    {
      "entryType": "item",
      "entryContent": {
        "imageURL": "https://archive.org/download/LFAType0039/LFA_Type_0039_001.jpg",
        "title": "Recta: Creazioni originali della",
        "newItem": 0
      },
      "entryURL": "LetArcV1_details.html?LFAitemID=lfa_type_0039&LFAPics=Yes"
    },
    {
      "entryType": "item",
      "entryContent": {
        "imageURL": "https://archive.org/download/LFAType0043/LFA_Type_0043_001.jpg",
        "title": "Recta: Tonda Chiara",
        "newItem": 0
      },
      "entryURL": "LetArcV1_details.html?LFAitemID=lfa_type_0043&LFAPics=Yes"
    },
    {
      "entryType": "item",
      "entryContent": {
        "imageURL": "https://archive.org/download/LFAType0049/LFA_Type_0049_001.jpg",
        "title": "Stop",
        "newItem": 0
      },
      "entryURL": "LetArcV1_details.html?LFAitemID=lfa_type_0049&LFAPics=Yes"
    },
    {
      "entryType": "item",
      "entryContent": {
        "imageURL": "https://archive.org/download/LFAType0051/LFA_Type_0051_001.jpg",
        "title": "Torino: roman, roman italic",
        "newItem": 0
      },
      "entryURL": "LetArcV1_details.html?LFAitemID=lfa_type_0051&LFAPics=Yes"
    },
    {
      "entryType": "item",
      "entryContent": {
        "imageURL": "https://archive.org/download/LFAType0056/LFA_Type_0056_001.jpg",
        "title": "Nebiolo Caratteri Legno",
        "newItem": 0
      },
      "entryURL": "LetArcV1_details.html?LFAitemID=lfa_type_0056&LFAPics=Yes"
    },
    {
      "entryType": "item",
      "entryContent": {
        "imageURL": "https://archive.org/download/LFAType0065/LFA_Type_0065_001.jpg",
        "title": "Antique Olive Série Grasse",
        "newItem": 0
      },
      "entryURL": "LetArcV1_details.html?LFAitemID=lfa_type_0065&LFAPics=Yes"
    },
    {
      "entryType": "item",
      "entryContent": {
        "imageURL": "https://archive.org/download/LFAType0085/LFA_Type_0085_001.jpg",
        "title": "Authors Roman Adstyle and the Authors Oldstyle",
        "newItem": 0
      },
      "entryURL": "LetArcV1_details.html?LFAitemID=lfa_type_0085&LFAPics=Yes"
    },
    {
      "entryType": "item",
      "entryContent": {
        "imageURL": "https://archive.org/download/LFAType0089/LFA_Type_0089_001.jpg",
        "title": "Cooper Family: Cooper Italic is Ready Now!",
        "newItem": 0
      },
      "entryURL": "LetArcV1_details.html?LFAitemID=lfa_type_0089&LFAPics=Yes"
    },
    {
      "entryType": "item",
      "entryContent": {
        "imageURL": "https://archive.org/download/LFAVenezky0011/LFA_Venezky_0011_001.jpg",
        "title": "Weird America",
        "newItem": 1
      },
      "entryURL": "LetArcV1_details.html?LFAitemID=lfa_venezky_0011&LFAPics=Yes"
    },
    {
      "entryType": "item",
      "entryContent": {
        "imageURL": "https://archive.org/download/LFAVenezky0025/LFA_Venezky_0025_001.jpg",
        "title": "Search Light: Consciousness at the Millenium (Event Poster)",
        "newItem": 1
      },
      "entryURL": "LetArcV1_details.html?LFAitemID=lfa_venezky_0025&LFAPics=Yes"
    },
    {
      "entryType": "item",
      "entryContent": {
        "imageURL": "https://archive.org/download/LFAVenezky0088/LFA_Venezky_0088_001.jpg",
        "title": "Process for The Grateful Palate: “Behold!”",
        "newItem": 1
      },
      "entryURL": "LetArcV1_details.html?LFAitemID=lfa_venezky_0088&LFAPics=Yes"
    },
    {
      "entryType": "item",
      "entryContent": {
        "imageURL": "https://archive.org/download/LFAVenezky0101/LFA_Venezky_0101_001.jpg",
        "title": "(Watches)",
        "newItem": 1
      },
      "entryURL": "LetArcV1_details.html?LFAitemID=lfa_venezky_0101&LFAPics=Yes"
    },
    {
      "entryType": "item",
      "entryContent": {
        "imageURL": "https://archive.org/download/LFAVenezky0103/LFA_Venezky_0103_001.jpg",
        "title": "(Helvetica Bold Type Specimen)",
        "newItem": 1
      },
      "entryURL": "LetArcV1_details.html?LFAitemID=lfa_venezky_0103&LFAPics=Yes"
    },
    {
      "entryType": "item",
      "entryContent": {
        "imageURL": "https://archive.org/download/LFAVenezky0168/LFA_Venezky_0168_001.jpg",
        "title": "CCA The Graduate Program in Design Thesis Events Card 2008",
        "newItem": 1
      },
      "entryURL": "LetArcV1_details.html?LFAitemID=lfa_venezky_0168&LFAPics=Yes"
    },
    {
      "entryType": "table",
      "entryContent": {
        "tableID": "t_lfa_amelia_201810061624",
        "tableName": "Uppercase A",
        "tableOwnerName": "Amelia Grounds"
      },
      "entryURL": "table.html?tableid=t_lfa_amelia_201810061624"
    },
    {
      "entryType": "table",
      "entryContent": {
        "tableID": "t_lfa_kate_201810070900",
        "tableName": "An Aesthetic Whole",
        "tableOwnerName": "Kate Goad"
      },
      "entryURL": "table.html?tableid=t_lfa_kate_201810070900"
    },
    {
      "entryType": "search",
      "entryContent": {
        "searchText": "More than a magazine, explore our Emigre collection"
      },
      "entryURL": "search.html?searchType=1&searchText=Emigre"
    },
    {
      "entryType": "search",
      "entryContent": {
        "searchText": "English Type Specimens"
      },
      "entryURL": "search.html?searchType=3&dims=Work%20type,country&vals0=Type%20Specimen&vals1=England,United%20Kingdom"
    },
    {
      "entryType": "search",
      "entryContent": {
        "searchText": "The prolific work of W A Dwiggins"
      },
      "entryURL": "search.html?searchType=2&dim=Creator&vals=Dwiggins,%20W%20A"
    }
  ]
}
